pyravelry/__init__.py
pyravelry/client.py
pyravelry/settings.py
pyravelry/endpoints/__init__.py
pyravelry/endpoints/base.py
pyravelry/endpoints/color_families.py
pyravelry/endpoints/comments.py
pyravelry/endpoints/current_user.py
pyravelry/endpoints/fiber_attributes.py
pyravelry/endpoints/fiber_categories.py
pyravelry/endpoints/people.py
pyravelry/endpoints/search.py
pyravelry/endpoints/yarn_attributes.py
pyravelry/endpoints/yarn_companies.py
pyravelry/endpoints/yarn_weights.py
pyravelry/models/__init__.py
pyravelry/models/base.py
pyravelry/models/colorfamily.py
pyravelry/models/colorway.py
pyravelry/models/comment.py
pyravelry/models/craft.py
pyravelry/models/fiberattribute.py
pyravelry/models/fiberattributegroup.py
pyravelry/models/fibercategory.py
pyravelry/models/fibertype.py
pyravelry/models/pack.py
pyravelry/models/photo.py
pyravelry/models/project.py
pyravelry/models/socialsite.py
pyravelry/models/tool.py
pyravelry/models/user.py
pyravelry/models/usersite.py
pyravelry/models/yarn.py
pyravelry/models/yarnattributegroup.py
pyravelry/models/yarncompany.py
pyravelry/models/yarncountry.py
pyravelry/models/yarnfiber.py
pyravelry/models/yarnprovenance.py
pyravelry/models/yarnweight.py
pyravelry/models/custom_models/__init__.py
pyravelry/models/custom_models/identifiers.py
pyravelry/models/custom_models/paginator.py
pyravelry/models/custom_models/search.py
pyravelry/models/custom_models/yarncompany.py
pyravelry-0.0.5.dist-info/METADATA
pyravelry-0.0.5.dist-info/WHEEL
pyravelry-0.0.5.dist-info/licenses/LICENSE
pyravelry-0.0.5.dist-info/RECORD
