Metadata-Version: 2.4
Name: pyravelry
Version: 0.0.5
Summary: Python wrapper for the Ravelry API, which is a database of knitting / crocheting patterns.
Project-URL: Homepage, https://theuerc.github.io/pyravelry/
Project-URL: Repository, https://github.com/theuerc/pyravelry
Project-URL: Documentation, https://theuerc.github.io/pyravelry/
Author-email: Coulton Theuer <theuerc@umich.edu>
License-File: LICENSE
Keywords: python
Classifier: Intended Audience :: Developers
Classifier: Programming Language :: Python
Classifier: Programming Language :: Python :: 3
Classifier: Programming Language :: Python :: 3.10
Classifier: Programming Language :: Python :: 3.11
Classifier: Programming Language :: Python :: 3.12
Classifier: Programming Language :: Python :: 3.13
Classifier: Programming Language :: Python :: 3.14
Classifier: Topic :: Software Development :: Libraries :: Python Modules
Requires-Python: <4.0,>=3.10
Requires-Dist: hishel[httpx]>=1.1.7
Requires-Dist: pydantic-settings>=2.12.0
Requires-Dist: pydantic>=2.12.5
